comch/__init__.py
comch/barratt_eccles/__init__.py
comch/barratt_eccles/barratt_eccles.py
comch/barratt_eccles/tests/__init__.py
comch/barratt_eccles/tests/test_barratt_eccles.py
comch/cubical/__init__.py
comch/cubical/cubical.py
comch/cubical/tests/__init__.py
comch/cubical/tests/test_cubical.py
comch/free_module/__init__.py
comch/free_module/free_module.py
comch/free_module/tests/__init__.py
comch/free_module/tests/test_free_module.py
comch/necklical/__init__.py
comch/necklical/necklical.py
comch/simplicial/__init__.py
comch/simplicial/simplicial.py
comch/simplicial/tests/__init__.py
comch/simplicial/tests/test_simplicial.py
comch/surjection/__init__.py
comch/surjection/surjection.py
comch/surjection/tests/__init__.py
comch/surjection/tests/test_surjection.py
comch/symmetric/__init__.py
comch/symmetric/symmetric.py
comch/symmetric/tests/__init__.py
comch/symmetric/tests/test_symmetric.py
comch/utils/__init__.py
comch/utils/utils.py
comch-0.1.4.dist-info/LICENSE
comch-0.1.4.dist-info/METADATA
comch-0.1.4.dist-info/WHEEL
comch-0.1.4.dist-info/top_level.txt
comch-0.1.4.dist-info/RECORD
