Metadata-Version: 2.1
Name: comch
Version: 0.1.4
Summary: A specialized computer algebra system for the study of commutativity up to coherent homotopies
Home-page: UNKNOWN
Author: Anibal M. Medina-Mardones
Author-email: ammedmar@gmail.com
License: UNKNOWN
Platform: UNKNOWN
Classifier: Programming Language :: Python :: 3
Classifier: License :: OSI Approved :: MIT License
Classifier: Operating System :: OS Independent
Requires-Python: >=3
